assessment/__init__.py
assessment/models.py
assessment/serializers.py
assessment/settings.py
assessment/migrations/0001_initial.py
assessment/migrations/0002_auto_20170811_1922.py
assessment/migrations/0003_remove_surveytranslation_slug.py
assessment/migrations/__init__.py
assessment/tests/__init__.py
assessment/tests/test_answer.py
assessment/tests/test_choice.py
assessment/tests/test_question.py
assessment/tests/test_result.py
assessment/tests/test_survey.py
assessment/urls/__init__.py
assessment/urls/api/__init__.py
assessment/urls/api/answer.py
assessment/urls/api/choice.py
assessment/urls/api/question.py
assessment/urls/api/result.py
assessment/urls/api/survey.py
assessment/views/__init__.py
assessment/views/api/__init__.py
assessment/views/api/answer.py
assessment/views/api/choice.py
assessment/views/api/question.py
assessment/views/api/result.py
assessment/views/api/survey.py
demo/__init__.py
demo/manage.py
demo/settings.py
demo/urls.py
demo/wsgi.py
django_assessment-0.3.1.dist-info/DESCRIPTION.rst
django_assessment-0.3.1.dist-info/METADATA
django_assessment-0.3.1.dist-info/RECORD
django_assessment-0.3.1.dist-info/WHEEL
django_assessment-0.3.1.dist-info/metadata.json
django_assessment-0.3.1.dist-info/top_level.txt
