Metadata-Version: 2.0
Name: django-assessment
Version: 0.3.1
Summary: Django Assessment package
Home-page: https://github.com/vandorjw/django-assessment
Author: Joost VanDorp
Author-email: joostvandorp@gmail.com
License: MIT
Keywords: django,assessment,quiz
Platform: UNKNOWN
Classifier: Framework :: Django
Classifier: Development Status :: 1 - Planning
Classifier: Environment :: Web Environment
Classifier: Programming Language :: Python
Classifier: Programming Language :: Python :: 3
Classifier: Intended Audience :: Developers
Classifier: Operating System :: OS Independent
Classifier: License :: OSI Approved :: MIT License
Classifier: Topic :: Software Development :: Libraries :: Python Modules
Requires-Dist: Django (>=1.8)
Requires-Dist: djangorestframework (>=3.4)
Requires-Dist: Markdown (>=2.6)
Requires-Dist: django-filter (>=1.0)
Requires-Dist: django-parler (>=1.8)
Requires-Dist: django-parler-rest (>=1.4)
Requires-Dist: django-cors-headers (>=2.0)
